[{"id_usr":"2","fecha_prestamo":"2019-04-18 00:00:00","monto":"5000","monto_dev":"5850","plazo":"2019-01-16 00:00:00","estado":"0"},{"id_usr":"5","fecha_prestamo":"2019-01-21 00:00:00","monto":"10000","monto_dev":"11350","plazo":"2019-01-22 00:00:00","estado":"0"},{"id_usr":"9","fecha_prestamo":"2019-01-18 00:00:00","monto":"20000","monto_dev":"22350","plazo":"2019-01-16 00:00:00","estado":"0"},{"id_usr":"10","fecha_prestamo":"2019-04-18 00:00:00","monto":"5000","monto_dev":"5850","plazo":"2019-01-16 00:00:00","estado":"0"},{"id_usr":"4","fecha_prestamo":"2019-01-21 00:00:00","monto":"10000","monto_dev":"11350","plazo":"2019-01-22 00:00:00","estado":"0"},{"id_usr":"6","fecha_prestamo":"2019-01-18 00:00:00","monto":"20000","monto_dev":"22350","plazo":"2019-01-16 00:00:00","estado":"0"}]